teemann/__init__.py
teemann/currentcps/__init__.py
teemann/currentcps/app.py
teemann/currentcps/view.py
teemann/currentcps/templates/cpwidget.xml
pyplanet_currentcps-1.1.0.dist-info/LICENSE
pyplanet_currentcps-1.1.0.dist-info/METADATA
pyplanet_currentcps-1.1.0.dist-info/WHEEL
pyplanet_currentcps-1.1.0.dist-info/top_level.txt
pyplanet_currentcps-1.1.0.dist-info/RECORD
