Metadata-Version: 2.1
Name: pyplanet-currentcps
Version: 1.1.0
Summary: Current CP widget, useful for RPG servers, App for PyPlanet Server Controller
Home-page: https://github.com/teemann/currentcps
Author: teemann
Author-email: teemann100@gmail.com
License: GNU General Public License v3 (GPLv3)
Keywords: maniaplanet,pyplanet,rpg,checkpoint
Platform: UNKNOWN
Classifier: License :: OSI Approved :: GNU General Public License v3 (GPLv3)
Classifier: Development Status :: 4 - Beta
Classifier: Programming Language :: Python :: 3
Classifier: Programming Language :: Python :: 3.5
Classifier: Programming Language :: Python :: 3.6
Classifier: Programming Language :: Python :: 3 :: Only
Classifier: Operating System :: OS Independent
Classifier: Topic :: Internet
Classifier: Topic :: Software Development
Classifier: Topic :: Games/Entertainment
Classifier: Topic :: Software Development :: Libraries :: Application Frameworks
Classifier: Topic :: Software Development :: Libraries :: Python Modules
Classifier: Intended Audience :: System Administrators
Classifier: Intended Audience :: Developers
Requires-Dist: pyplanet
